coremltools/__init__.py
coremltools/libcoremlpython.so
coremltools/libmilstoragepython.so
coremltools/libmodelpackage.so
coremltools/version.py
coremltools/_deps/__init__.py
coremltools/converters/__init__.py
coremltools/converters/_converters_entry.py
coremltools/converters/_profile_utils.py
coremltools/converters/libsvm/__init__.py
coremltools/converters/libsvm/_libsvm_converter.py
coremltools/converters/libsvm/_libsvm_util.py
coremltools/converters/mil/__init__.py
coremltools/converters/mil/_deployment_compatibility.py
coremltools/converters/mil/conftest.py
coremltools/converters/mil/converter.py
coremltools/converters/mil/input_types.py
coremltools/converters/mil/test_flexible_shape_inputs.py
coremltools/converters/mil/testing_reqs.py
coremltools/converters/mil/testing_utils.py
coremltools/converters/mil/backend/__init__.py
coremltools/converters/mil/backend/backend_helper.py
coremltools/converters/mil/backend/mil/__init__.py
coremltools/converters/mil/backend/mil/helper.py
coremltools/converters/mil/backend/mil/load.py
coremltools/converters/mil/backend/mil/test_helper.py
coremltools/converters/mil/backend/mil/test_model_input_params.py
coremltools/converters/mil/backend/mil/passes/__init__.py
coremltools/converters/mil/backend/mil/passes/adjust_io_to_supported_types.py
coremltools/converters/mil/backend/mil/passes/fuse_activation_silu.py
coremltools/converters/mil/backend/mil/passes/insert_image_preprocessing_op.py
coremltools/converters/mil/backend/mil/passes/mil_passes.py
coremltools/converters/mil/backend/mil/passes/sanitize_name_strings.py
coremltools/converters/mil/backend/mil/passes/test_passes.py
coremltools/converters/mil/backend/nn/__init__.py
coremltools/converters/mil/backend/nn/load.py
coremltools/converters/mil/backend/nn/mil_to_nn_mapping_registry.py
coremltools/converters/mil/backend/nn/op_mapping.py
coremltools/converters/mil/backend/nn/passes/__init__.py
coremltools/converters/mil/backend/nn/passes/alert_return_type_cast.py
paddle2coreml-6.2.dist-info/LICENSE.txt
paddle2coreml-6.2.dist-info/METADATA
paddle2coreml-6.2.dist-info/WHEEL
paddle2coreml-6.2.dist-info/top_level.txt
paddle2coreml-6.2.dist-info/RECORD
